capon/__init__.py
capon/portfolio.py
capon/preprocessing.py
capon/wrappers.py
capon/backends/__init__.py
capon/backends/nasdaq.py
capon/backends/otcmarkets.py
capon/backends/utils.py
capon/backends/yahoo.py
capon/datasets/__init__.py
capon/datasets/common.py
capon/datasets/metadata.py
capon/labs/__init__.py
capon/labs/dividends.py
capon/labs/download.py
capon/labs/yf_earning_calls.py
capon/resources/metadata/stocks.metadata.x09786.(20220630.142223).csv.gz
capon/visualization/__init__.py
capon/visualization/altairplotter.py
capon/visualization/common.py
capon/visualization/history.py
capon/visualization/portfolio.py
capon/visualization/template.py
capon-0.0.94.dist-info/LICENSE
capon-0.0.94.dist-info/METADATA
capon-0.0.94.dist-info/WHEEL
capon-0.0.94.dist-info/top_level.txt
capon-0.0.94.dist-info/RECORD
