Metadata-Version: 2.1
Name: capon
Version: 0.0.94
Summary: Capital Market in Python
Home-page: https://github.com/gialdetti/capon/
Author: Eyal Gal
Author-email: eyalgl@gmail.com
Keywords: capital markets,stocks,stock market,finance,dataset,portfolio,dashboard,yahoo finance
Classifier: Programming Language :: Python :: 3.10
Classifier: License :: OSI Approved :: GNU General Public License v3 (GPLv3)
License-File: LICENSE
Requires-Dist: requests >=2.31.0
Requires-Dist: numpy >=1.26.4
Requires-Dist: pandas >=1.5.0
Requires-Dist: tqdm >=4.66.3
Requires-Dist: joblib
Provides-Extra: dev
Requires-Dist: notebook ; extra == 'dev'
Requires-Dist: matplotlib ; extra == 'dev'
Requires-Dist: ipywidgets ; extra == 'dev'
Requires-Dist: seaborn ; extra == 'dev'
Requires-Dist: themes ; extra == 'dev'
Requires-Dist: scikit-learn >=1.5.0 ; extra == 'dev'
Requires-Dist: altair ; extra == 'dev'
Requires-Dist: black >=24.3.0 ; extra == 'dev'
Requires-Dist: pytest ; extra == 'dev'
Requires-Dist: ipython ; extra == 'dev'
Requires-Dist: tox ; extra == 'dev'
Provides-Extra: docs
Requires-Dist: black >=24.3.0 ; extra == 'docs'
Provides-Extra: test
Requires-Dist: pytest ; extra == 'test'
Requires-Dist: ipython ; extra == 'test'
Requires-Dist: tox ; extra == 'test'
